counter/rtl/counter.svh
module counter(
input logic rst,
input logic clock,
input logic enable,
output logic [7:0] count_value
);

// initialization
initial begin 
    count_value = 8'd0;
end

//
always_ff @(posedge clock or posedge rst) begin
    if (rst) begin
        count_value <=8'd0;
    end else if (enable) begin
        count_value<=count_value+1'd1;
    end

end

endmodule

counter/tb/counter_tb.sv
`timescale 1ns/1ps

module counter_tb;

    // Parameters for easy modification
    parameter int CYCLE_TIME_NS   = 10;      // 100 MHz clock
    parameter int HALF_CYCLE_NS   = CYCLE_TIME_NS / 2;
    parameter int TOTAL_CYCLES    = 400;
    parameter int RESET_CYCLE     = 50;
    parameter int TOGGLE_ENABLE_0  = 10;
    parameter int TOGGLE_ENABLE_1  = 100;
    parameter int TOGGLE_ENABLE_2  = 160;
    parameter int TOGGLE_ENABLE_3  = 380;
   
   // I/O for the uut (see uut)
    logic       enable;
    logic       rst;
    logic       clock;
    logic [7:0] out;

// assign I/O to ports
    counter uut (
        .enable(enable),
        .rst(rst),
        .clock(clock),
        .count_value(out)
    );


    logic [7:0] expected;
    int cycle_count;

    initial begin
        $dumpfile("build/counter_tb.vcd");
        $dumpvars(0, counter_tb);
    end

    // Clock generation
    initial begin
        clock = 0;
        forever begin
            #(HALF_CYCLE_NS) clock = ~clock;
        end
    end

    // Stimulus
    initial begin

        enable               = 1'b0;
        rst                  = 1'b1;   // start in reset for deterministic initialization
        expected             = 0;
        cycle_count          = 0;

        $display("running counter TB");
        $display("time(ns) cycle rst enable expected out");
        $monitor("%0t %0d %b %b %0d %0d", $time, cycle_count, rst, enable, expected, out);

        wait (clock == 1'b1);
        @(posedge clock);

        while (cycle_count < TOTAL_CYCLES) begin
            

            // reset active for one cycle at RESET_CYCLE
            if (cycle_count == RESET_CYCLE) begin
                rst = 1'b1;
            end else begin
                rst = 1'b0;
            end

            // toggle enable
            if ((cycle_count == TOGGLE_ENABLE_0) || (cycle_count == TOGGLE_ENABLE_1) ||(cycle_count == TOGGLE_ENABLE_2) || (cycle_count == TOGGLE_ENABLE_3) ) begin
                enable = ~enable;
            end

            // compute expected value for next cycle
            if (rst) begin
                expected = 0;
            end else if (enable) begin
                expected = expected + 1;
            end

            @(posedge clock);

            // check output after clock edge
            if (out !== expected)  
                $error("Mismatch at cycle %0d: expected=%0d / out=%0d",cycle_count, expected,  out);

            cycle_count++;
        end

        # (CYCLE_TIME_NS);
        $display("Simulation complete after %0d cycles", TOTAL_CYCLES);
        $finish;
    end

endmodule

counter/build/counter_tb.vcd
$date
	Wed Aug  5 00:26:33 2026
$end
$version
	Icarus Verilog
$end
$timescale
	1ps
$end
$scope module counter_tb $end
$var wire 8 ! out [7:0] $end
$var parameter 32 " CYCLE_TIME_NS $end
$var parameter 32 # HALF_CYCLE_NS $end
$var parameter 32 $ RESET_CYCLE $end
$var parameter 32 % TOGGLE_ENABLE_0 $end
$var parameter 32 & TOGGLE_ENABLE_1 $end
$var parameter 32 ' TOGGLE_ENABLE_2 $end
$var parameter 32 ( TOGGLE_ENABLE_3 $end
$var parameter 32 ) TOTAL_CYCLES $end
$var reg 1 * clock $end
$var reg 1 + enable $end
$var reg 8 , expected [7:0] $end
$var reg 1 - rst $end
$var integer 32 . cycle_count [31:0] $end
$scope module uut $end
$var wire 1 * clock $end
$var wire 1 + enable $end
$var wire 1 - rst $end
$var reg 8 / count_value [7:0] $end
$upscope $end
$upscope $end
$enddefinitions $end
$comment Show the parameter values. $end
$dumpall
b110010000 )
b101111100 (
b10100000 '
b1100100 &
b1010 %
b110010 $
b101 #
b1010 "
$end
#0
$dumpvars
b0 /
b0 .
1-
b0 ,
0+
0*
b0 !
$end
#5000
1*
#10000
0*
#15000
0-
1*
#20000
0*
#25000
b1 .
1*
#30000
0*
#35000
b10 .
1*
#40000
0*
#45000
b11 .
1*
#50000
0*
#55000
b100 .
1*
#60000
0*
#65000
b101 .
1*
#70000
0*
#75000
b110 .
1*
#80000
0*
#85000
b111 .
1*
#90000
0*
#95000
b1000 .
1*
#100000
0*
#105000
b1001 .
1*
#110000
0*
#115000
b1 !
b1 /
b1 ,
1+
b1010 .
1*
#120000
0*
#125000
b10 !
b10 /
b10 ,
b1011 .
1*
#130000
0*
#135000
b11 !
b11 /
b11 ,
b1100 .
1*
#140000
0*
#145000
b100 !
b100 /
b100 ,
b1101 .
1*
#150000
0*
#155000
b101 !
b101 /
b101 ,
b1110 .
1*
#160000
0*
#165000
b110 !
b110 /
b110 ,
b1111 .
1*
#170000
0*
#175000
b111 !
b111 /
b111 ,
b10000 .
1*
#180000
0*
#185000
b1000 !
b1000 /
b1000 ,
b10001 .
1*
#190000
0*
#195000
b1001 !
b1001 /
b1001 ,
b10010 .
1*
#200000
0*
#205000
b1010 !
b1010 /
b1010 ,
b10011 .
1*
#210000
0*
#215000
b1011 !
b1011 /
b1011 ,
b10100 .
1*
#220000
0*
#225000
b1100 !
b1100 /
b1100 ,
b10101 .
1*
#230000
0*
#235000
b1101 !
b1101 /
b1101 ,
b10110 .
1*
#240000
0*
#245000
b1110 !
b1110 /
b1110 ,
b10111 .
1*
#250000
0*
#255000
b1111 !
b1111 /
b1111 ,
b11000 .
1*
#260000
0*
#265000
b10000 !
b10000 /
b10000 ,
b11001 .
1*
#270000
0*
#275000
b10001 !
b10001 /
b10001 ,
b11010 .
1*
#280000
0*
#285000
b10010 !
b10010 /
b10010 ,
b11011 .
1*
#290000
0*
#295000
b10011 !
b10011 /
b10011 ,
b11100 .
1*
#300000
0*
#305000
b10100 !
b10100 /
b10100 ,
b11101 .
1*
#310000
0*
#315000
b10101 !
b10101 /
b10101 ,
b11110 .
1*
#320000
0*
#325000
b10110 !
b10110 /
b10110 ,
b11111 .
1*
#330000
0*
#335000
b10111 !
b10111 /
b10111 ,
b100000 .
1*
#340000
0*
#345000
b11000 !
b11000 /
b11000 ,
b100001 .
1*
#350000
0*
#355000
b11001 !
b11001 /
b11001 ,
b100010 .
1*
#360000
0*
#365000
b11010 !
b11010 /
b11010 ,
b100011 .
1*
#370000
0*
#375000
b11011 !
b11011 /
b11011 ,
b100100 .
1*
#380000
0*
#385000
b11100 !
b11100 /
b11100 ,
b100101 .
1*
#390000
0*
#395000
b11101 !
b11101 /
b11101 ,
b100110 .
1*
#400000
0*
#405000
b11110 !
b11110 /
b11110 ,
b100111 .
1*
#410000
0*
#415000
b11111 !
b11111 /
b11111 ,
b101000 .
1*
#420000
0*
#425000
b100000 !
b100000 /
b100000 ,
b101001 .
1*
#430000
0*
#435000
b100001 !
b100001 /
b100001 ,
b101010 .
1*
#440000
0*
#445000
b100010 !
b100010 /
b100010 ,
b101011 .
1*
#450000
0*
#455000
b100011 !
b100011 /
b100011 ,
b101100 .
1*
#460000
0*
#465000
b100100 !
b100100 /
b100100 ,
b101101 .
1*
#470000
0*
#475000
b100101 !
b100101 /
b100101 ,
b101110 .
1*
#480000
0*
#485000
b100110 !
b100110 /
b100110 ,
b101111 .
1*
#490000
0*
#495000
b100111 !
b100111 /
b100111 ,
b110000 .
1*
#500000
0*
#505000
b101000 !
b101000 /
b101000 ,
b110001 .
1*
#510000
0*
#515000
b0 !
b0 /
b0 ,
1-
b110010 .
1*
#520000
0*
#525000
b1 !
b1 /
b1 ,
0-
b110011 .
1*
#530000
0*
#535000
b10 !
b10 /
b10 ,
b110100 .
1*
#540000
0*
#545000
b11 !
b11 /
b11 ,
b110101 .
1*
#550000
0*
#555000
b100 !
b100 /
b100 ,
b110110 .
1*
#560000
0*
#565000
b101 !
b101 /
b101 ,
b110111 .
1*
#570000
0*
#575000
b110 !
b110 /
b110 ,
b111000 .
1*
#580000
0*
#585000
b111 !
b111 /
b111 ,
b111001 .
1*
#590000
0*
#595000
b1000 !
b1000 /
b1000 ,
b111010 .
1*
#600000
0*
#605000
b1001 !
b1001 /
b1001 ,
b111011 .
1*
#610000
0*
#615000
b1010 !
b1010 /
b1010 ,
b111100 .
1*
#620000
0*
#625000
b1011 !
b1011 /
b1011 ,
b111101 .
1*
#630000
0*
#635000
b1100 !
b1100 /
b1100 ,
b111110 .
1*
#640000
0*
#645000
b1101 !
b1101 /
b1101 ,
b111111 .
1*
#650000
0*
#655000
b1110 !
b1110 /
b1110 ,
b1000000 .
1*
#660000
0*
#665000
b1111 !
b1111 /
b1111 ,
b1000001 .
1*
#670000
0*
#675000
b10000 !
b10000 /
b10000 ,
b1000010 .
1*
#680000
0*
#685000
b10001 !
b10001 /
b10001 ,
b1000011 .
1*
#690000
0*
#695000
b10010 !
b10010 /
b10010 ,
b1000100 .
1*
#700000
0*
#705000
b10011 !
b10011 /
b10011 ,
b1000101 .
1*
#710000
0*
#715000
b10100 !
b10100 /
b10100 ,
b1000110 .
1*
#720000
0*
#725000
b10101 !
b10101 /
b10101 ,
b1000111 .
1*
#730000
0*
#735000
b10110 !
b10110 /
b10110 ,
b1001000 .
1*
#740000
0*
#745000
b10111 !
b10111 /
b10111 ,
b1001001 .
1*
#750000
0*
#755000
b11000 !
b11000 /
b11000 ,
b1001010 .
1*
#760000
0*
#765000
b11001 !
b11001 /
b11001 ,
b1001011 .
1*
#770000
0*
#775000
b11010 !
b11010 /
b11010 ,
b1001100 .
1*
#780000
0*
#785000
b11011 !
b11011 /
b11011 ,
b1001101 .
1*
#790000
0*
#795000
b11100 !
b11100 /
b11100 ,
b1001110 .
1*
#800000
0*
#805000
b11101 !
b11101 /
b11101 ,
b1001111 .
1*
#810000
0*
#815000
b11110 !
b11110 /
b11110 ,
b1010000 .
1*
#820000
0*
#825000
b11111 !
b11111 /
b11111 ,
b1010001 .
1*
#830000
0*
#835000
b100000 !
b100000 /
b100000 ,
b1010010 .
1*
#840000
0*
#845000
b100001 !
b100001 /
b100001 ,
b1010011 .
1*
#850000
0*
#855000
b100010 !
b100010 /
b100010 ,
b1010100 .
1*
#860000
0*
#865000
b100011 !
b100011 /
b100011 ,
b1010101 .
1*
#870000
0*
#875000
b100100 !
b100100 /
b100100 ,
b1010110 .
1*
#880000
0*
#885000
b100101 !
b100101 /
b100101 ,
b1010111 .
1*
#890000
0*
#895000
b100110 !
b100110 /
b100110 ,
b1011000 .
1*
#900000
0*
#905000
b100111 !
b100111 /
b100111 ,
b1011001 .
1*
#910000
0*
#915000
b101000 !
b101000 /
b101000 ,
b1011010 .
1*
#920000
0*
#925000
b101001 !
b101001 /
b101001 ,
b1011011 .
1*
#930000
0*
#935000
b101010 !
b101010 /
b101010 ,
b1011100 .
1*
#940000
0*
#945000
b101011 !
b101011 /
b101011 ,
b1011101 .
1*
#950000
0*
#955000
b101100 !
b101100 /
b101100 ,
b1011110 .
1*
#960000
0*
#965000
b101101 !
b101101 /
b101101 ,
b1011111 .
1*
#970000
0*
#975000
b101110 !
b101110 /
b101110 ,
b1100000 .
1*
#980000
0*
#985000
b101111 !
b101111 /
b101111 ,
b1100001 .
1*
#990000
0*
#995000
b110000 !
b110000 /
b110000 ,
b1100010 .
1*
#1000000
0*
#1005000
b110001 !
b110001 /
b110001 ,
b1100011 .
1*
#1010000
0*
#1015000
0+
b1100100 .
1*
#1020000
0*
#1025000
b1100101 .
1*
#1030000
0*
#1035000
b1100110 .
1*
#1040000
0*
#1045000
b1100111 .
1*
#1050000
0*
#1055000
b1101000 .
1*
#1060000
0*
#1065000
b1101001 .
1*
#1070000
0*
#1075000
b1101010 .
1*
#1080000
0*
#1085000
b1101011 .
1*
#1090000
0*
#1095000
b1101100 .
1*
#1100000
0*
#1105000
b1101101 .
1*
#1110000
0*
#1115000
b1101110 .
1*
#1120000
0*
#1125000
b1101111 .
1*
#1130000
0*
#1135000
b1110000 .
1*
#1140000
0*
#1145000
b1110001 .
1*
#1150000
0*
#1155000
b1110010 .
1*
#1160000
0*
#1165000
b1110011 .
1*
#1170000
0*
#1175000
b1110100 .
1*
#1180000
0*
#1185000
b1110101 .
1*
#1190000
0*
#1195000
b1110110 .
1*
#1200000
0*
#1205000
b1110111 .
1*
#1210000
0*
#1215000
b1111000 .
1*
#1220000
0*
#1225000
b1111001 .
1*
#1230000
0*
#1235000
b1111010 .
1*
#1240000
0*
#1245000
b1111011 .
1*
#1250000
0*
#1255000
b1111100 .
1*
#1260000
0*
#1265000
b1111101 .
1*
#1270000
0*
#1275000
b1111110 .
1*
#1280000
0*
#1285000
b1111111 .
1*
#1290000
0*
#1295000
b10000000 .
1*
#1300000
0*
#1305000
b10000001 .
1*
#1310000
0*
#1315000
b10000010 .
1*
#1320000
0*
#1325000
b10000011 .
1*
#1330000
0*
#1335000
b10000100 .
1*
#1340000
0*
#1345000
b10000101 .
1*
#1350000
0*
#1355000
b10000110 .
1*
#1360000
0*
#1365000
b10000111 .
1*
#1370000
0*
#1375000
b10001000 .
1*
#1380000
0*
#1385000
b10001001 .
1*
#1390000
0*
#1395000
b10001010 .
1*
#1400000
0*
#1405000
b10001011 .
1*
#1410000
0*
#1415000
b10001100 .
1*
#1420000
0*
#1425000
b10001101 .
1*
#1430000
0*
#1435000
b10001110 .
1*
#1440000
0*
#1445000
b10001111 .
1*
#1450000
0*
#1455000
b10010000 .
1*
#1460000
0*
#1465000
b10010001 .
1*
#1470000
0*
#1475000
b10010010 .
1*
#1480000
0*
#1485000
b10010011 .
1*
#1490000
0*
#1495000
b10010100 .
1*
#1500000
0*
#1505000
b10010101 .
1*
#1510000
0*
#1515000
b10010110 .
1*
#1520000
0*
#1525000
b10010111 .
1*
#1530000
0*
#1535000
b10011000 .
1*
#1540000
0*
#1545000
b10011001 .
1*
#1550000
0*
#1555000
b10011010 .
1*
#1560000
0*
#1565000
b10011011 .
1*
#1570000
0*
#1575000
b10011100 .
1*
#1580000
0*
#1585000
b10011101 .
1*
#1590000
0*
#1595000
b10011110 .
1*
#1600000
0*
#1605000
b10011111 .
1*
#1610000
0*
#1615000
b110010 !
b110010 /
b110010 ,
1+
b10100000 .
1*
#1620000
0*
#1625000
b110011 !
b110011 /
b110011 ,
b10100001 .
1*
#1630000
0*
#1635000
b110100 !
b110100 /
b110100 ,
b10100010 .
1*
#1640000
0*
#1645000
b110101 !
b110101 /
b110101 ,
b10100011 .
1*
#1650000
0*
#1655000
b110110 !
b110110 /
b110110 ,
b10100100 .
1*
#1660000
0*
#1665000
b110111 !
b110111 /
b110111 ,
b10100101 .
1*
#1670000
0*
#1675000
b111000 !
b111000 /
b111000 ,
b10100110 .
1*
#1680000
0*
#1685000
b111001 !
b111001 /
b111001 ,
b10100111 .
1*
#1690000
0*
#1695000
b111010 !
b111010 /
b111010 ,
b10101000 .
1*
#1700000
0*
#1705000
b111011 !
b111011 /
b111011 ,
b10101001 .
1*
#1710000
0*
#1715000
b111100 !
b111100 /
b111100 ,
b10101010 .
1*
#1720000
0*
#1725000
b111101 !
b111101 /
b111101 ,
b10101011 .
1*
#1730000
0*
#1735000
b111110 !
b111110 /
b111110 ,
b10101100 .
1*
#1740000
0*
#1745000
b111111 !
b111111 /
b111111 ,
b10101101 .
1*
#1750000
0*
#1755000
b1000000 !
b1000000 /
b1000000 ,
b10101110 .
1*
#1760000
0*
#1765000
b1000001 !
b1000001 /
b1000001 ,
b10101111 .
1*
#1770000
0*
#1775000
b1000010 !
b1000010 /
b1000010 ,
b10110000 .
1*
#1780000
0*
#1785000
b1000011 !
b1000011 /
b1000011 ,
b10110001 .
1*
#1790000
0*
#1795000
b1000100 !
b1000100 /
b1000100 ,
b10110010 .
1*
#1800000
0*
#1805000
b1000101 !
b1000101 /
b1000101 ,
b10110011 .
1*
#1810000
0*
#1815000
b1000110 !
b1000110 /
b1000110 ,
b10110100 .
1*
#1820000
0*
#1825000
b1000111 !
b1000111 /
b1000111 ,
b10110101 .
1*
#1830000
0*
#1835000
b1001000 !
b1001000 /
b1001000 ,
b10110110 .
1*
#1840000
0*
#1845000
b1001001 !
b1001001 /
b1001001 ,
b10110111 .
1*
#1850000
0*
#1855000
b1001010 !
b1001010 /
b1001010 ,
b10111000 .
1*
#1860000
0*
#1865000
b1001011 !
b1001011 /
b1001011 ,
b10111001 .
1*
#1870000
0*
#1875000
b1001100 !
b1001100 /
b1001100 ,
b10111010 .
1*
#1880000
0*
#1885000
b1001101 !
b1001101 /
b1001101 ,
b10111011 .
1*
#1890000
0*
#1895000
b1001110 !
b1001110 /
b1001110 ,
b10111100 .
1*
#1900000
0*
#1905000
b1001111 !
b1001111 /
b1001111 ,
b10111101 .
1*
#1910000
0*
#1915000
b1010000 !
b1010000 /
b1010000 ,
b10111110 .
1*
#1920000
0*
#1925000
b1010001 !
b1010001 /
b1010001 ,
b10111111 .
1*
#1930000
0*
#1935000
b1010010 !
b1010010 /
b1010010 ,
b11000000 .
1*
#1940000
0*
#1945000
b1010011 !
b1010011 /
b1010011 ,
b11000001 .
1*
#1950000
0*
#1955000
b1010100 !
b1010100 /
b1010100 ,
b11000010 .
1*
#1960000
0*
#1965000
b1010101 !
b1010101 /
b1010101 ,
b11000011 .
1*
#1970000
0*
#1975000
b1010110 !
b1010110 /
b1010110 ,
b11000100 .
1*
#1980000
0*
#1985000
b1010111 !
b1010111 /
b1010111 ,
b11000101 .
1*
#1990000
0*
#1995000
b1011000 !
b1011000 /
b1011000 ,
b11000110 .
1*
#2000000
0*
#2005000
b1011001 !
b1011001 /
b1011001 ,
b11000111 .
1*
#2010000
0*
#2015000
b1011010 !
b1011010 /
b1011010 ,
b11001000 .
1*
#2020000
0*
#2025000
b1011011 !
b1011011 /
b1011011 ,
b11001001 .
1*
#2030000
0*
#2035000
b1011100 !
b1011100 /
b1011100 ,
b11001010 .
1*
#2040000
0*
#2045000
b1011101 !
b1011101 /
b1011101 ,
b11001011 .
1*
#2050000
0*
#2055000
b1011110 !
b1011110 /
b1011110 ,
b11001100 .
1*
#2060000
0*
#2065000
b1011111 !
b1011111 /
b1011111 ,
b11001101 .
1*
#2070000
0*
#2075000
b1100000 !
b1100000 /
b1100000 ,
b11001110 .
1*
#2080000
0*
#2085000
b1100001 !
b1100001 /
b1100001 ,
b11001111 .
1*
#2090000
0*
#2095000
b1100010 !
b1100010 /
b1100010 ,
b11010000 .
1*
#2100000
0*
#2105000
b1100011 !
b1100011 /
b1100011 ,
b11010001 .
1*
#2110000
0*
#2115000
b1100100 !
b1100100 /
b1100100 ,
b11010010 .
1*
#2120000
0*
#2125000
b1100101 !
b1100101 /
b1100101 ,
b11010011 .
1*
#2130000
0*
#2135000
b1100110 !
b1100110 /
b1100110 ,
b11010100 .
1*
#2140000
0*
#2145000
b1100111 !
b1100111 /
b1100111 ,
b11010101 .
1*
#2150000
0*
#2155000
b1101000 !
b1101000 /
b1101000 ,
b11010110 .
1*
#2160000
0*
#2165000
b1101001 !
b1101001 /
b1101001 ,
b11010111 .
1*
#2170000
0*
#2175000
b1101010 !
b1101010 /
b1101010 ,
b11011000 .
1*
#2180000
0*
#2185000
b1101011 !
b1101011 /
b1101011 ,
b11011001 .
1*
#2190000
0*
#2195000
b1101100 !
b1101100 /
b1101100 ,
b11011010 .
1*
#2200000
0*
#2205000
b1101101 !
b1101101 /
b1101101 ,
b11011011 .
1*
#2210000
0*
#2215000
b1101110 !
b1101110 /
b1101110 ,
b11011100 .
1*
#2220000
0*
#2225000
b1101111 !
b1101111 /
b1101111 ,
b11011101 .
1*
#2230000
0*
#2235000
b1110000 !
b1110000 /
b1110000 ,
b11011110 .
1*
#2240000
0*
#2245000
b1110001 !
b1110001 /
b1110001 ,
b11011111 .
1*
#2250000
0*
#2255000
b1110010 !
b1110010 /
b1110010 ,
b11100000 .
1*
#2260000
0*
#2265000
b1110011 !
b1110011 /
b1110011 ,
b11100001 .
1*
#2270000
0*
#2275000
b1110100 !
b1110100 /
b1110100 ,
b11100010 .
1*
#2280000
0*
#2285000
b1110101 !
b1110101 /
b1110101 ,
b11100011 .
1*
#2290000
0*
#2295000
b1110110 !
b1110110 /
b1110110 ,
b11100100 .
1*
#2300000
0*
#2305000
b1110111 !
b1110111 /
b1110111 ,
b11100101 .
1*
#2310000
0*
#2315000
b1111000 !
b1111000 /
b1111000 ,
b11100110 .
1*
#2320000
0*
#2325000
b1111001 !
b1111001 /
b1111001 ,
b11100111 .
1*
#2330000
0*
#2335000
b1111010 !
b1111010 /
b1111010 ,
b11101000 .
1*
#2340000
0*
#2345000
b1111011 !
b1111011 /
b1111011 ,
b11101001 .
1*
#2350000
0*
#2355000
b1111100 !
b1111100 /
b1111100 ,
b11101010 .
1*
#2360000
0*
#2365000
b1111101 !
b1111101 /
b1111101 ,
b11101011 .
1*
#2370000
0*
#2375000
b1111110 !
b1111110 /
b1111110 ,
b11101100 .
1*
#2380000
0*
#2385000
b1111111 !
b1111111 /
b1111111 ,
b11101101 .
1*
#2390000
0*
#2395000
b10000000 !
b10000000 /
b10000000 ,
b11101110 .
1*
#2400000
0*
#2405000
b10000001 !
b10000001 /
b10000001 ,
b11101111 .
1*
#2410000
0*
#2415000
b10000010 !
b10000010 /
b10000010 ,
b11110000 .
1*
#2420000
0*
#2425000
b10000011 !
b10000011 /
b10000011 ,
b11110001 .
1*
#2430000
0*
#2435000
b10000100 !
b10000100 /
b10000100 ,
b11110010 .
1*
#2440000
0*
#2445000
b10000101 !
b10000101 /
b10000101 ,
b11110011 .
1*
#2450000
0*
#2455000
b10000110 !
b10000110 /
b10000110 ,
b11110100 .
1*
#2460000
0*
#2465000
b10000111 !
b10000111 /
b10000111 ,
b11110101 .
1*
#2470000
0*
#2475000
b10001000 !
b10001000 /
b10001000 ,
b11110110 .
1*
#2480000
0*
#2485000
b10001001 !
b10001001 /
b10001001 ,
b11110111 .
1*
#2490000
0*
#2495000
b10001010 !
b10001010 /
b10001010 ,
b11111000 .
1*
#2500000
0*
#2505000
b10001011 !
b10001011 /
b10001011 ,
b11111001 .
1*
#2510000
0*
#2515000
b10001100 !
b10001100 /
b10001100 ,
b11111010 .
1*
#2520000
0*
#2525000
b10001101 !
b10001101 /
b10001101 ,
b11111011 .
1*
#2530000
0*
#2535000
b10001110 !
b10001110 /
b10001110 ,
b11111100 .
1*
#2540000
0*
#2545000
b10001111 !
b10001111 /
b10001111 ,
b11111101 .
1*
#2550000
0*
#2555000
b10010000 !
b10010000 /
b10010000 ,
b11111110 .
1*
#2560000
0*
#2565000
b10010001 !
b10010001 /
b10010001 ,
b11111111 .
1*
#2570000
0*
#2575000
b10010010 !
b10010010 /
b10010010 ,
b100000000 .
1*
#2580000
0*
#2585000
b10010011 !
b10010011 /
b10010011 ,
b100000001 .
1*
#2590000
0*
#2595000
b10010100 !
b10010100 /
b10010100 ,
b100000010 .
1*
#2600000
0*
#2605000
b10010101 !
b10010101 /
b10010101 ,
b100000011 .
1*
#2610000
0*
#2615000
b10010110 !
b10010110 /
b10010110 ,
b100000100 .
1*
#2620000
0*
#2625000
b10010111 !
b10010111 /
b10010111 ,
b100000101 .
1*
#2630000
0*
#2635000
b10011000 !
b10011000 /
b10011000 ,
b100000110 .
1*
#2640000
0*
#2645000
b10011001 !
b10011001 /
b10011001 ,
b100000111 .
1*
#2650000
0*
#2655000
b10011010 !
b10011010 /
b10011010 ,
b100001000 .
1*
#2660000
0*
#2665000
b10011011 !
b10011011 /
b10011011 ,
b100001001 .
1*
#2670000
0*
#2675000
b10011100 !
b10011100 /
b10011100 ,
b100001010 .
1*
#2680000
0*
#2685000
b10011101 !
b10011101 /
b10011101 ,
b100001011 .
1*
#2690000
0*
#2695000
b10011110 !
b10011110 /
b10011110 ,
b100001100 .
1*
#2700000
0*
#2705000
b10011111 !
b10011111 /
b10011111 ,
b100001101 .
1*
#2710000
0*
#2715000
b10100000 !
b10100000 /
b10100000 ,
b100001110 .
1*
#2720000
0*
#2725000
b10100001 !
b10100001 /
b10100001 ,
b100001111 .
1*
#2730000
0*
#2735000
b10100010 !
b10100010 /
b10100010 ,
b100010000 .
1*
#2740000
0*
#2745000
b10100011 !
b10100011 /
b10100011 ,
b100010001 .
1*
#2750000
0*
#2755000
b10100100 !
b10100100 /
b10100100 ,
b100010010 .
1*
#2760000
0*
#2765000
b10100101 !
b10100101 /
b10100101 ,
b100010011 .
1*
#2770000
0*
#2775000
b10100110 !
b10100110 /
b10100110 ,
b100010100 .
1*
#2780000
0*
#2785000
b10100111 !
b10100111 /
b10100111 ,
b100010101 .
1*
#2790000
0*
#2795000
b10101000 !
b10101000 /
b10101000 ,
b100010110 .
1*
#2800000
0*
#2805000
b10101001 !
b10101001 /
b10101001 ,
b100010111 .
1*
#2810000
0*
#2815000
b10101010 !
b10101010 /
b10101010 ,
b100011000 .
1*
#2820000
0*
#2825000
b10101011 !
b10101011 /
b10101011 ,
b100011001 .
1*
#2830000
0*
#2835000
b10101100 !
b10101100 /
b10101100 ,
b100011010 .
1*
#2840000
0*
#2845000
b10101101 !
b10101101 /
b10101101 ,
b100011011 .
1*
#2850000
0*
#2855000
b10101110 !
b10101110 /
b10101110 ,
b100011100 .
1*
#2860000
0*
#2865000
b10101111 !
b10101111 /
b10101111 ,
b100011101 .
1*
#2870000
0*
#2875000
b10110000 !
b10110000 /
b10110000 ,
b100011110 .
1*
#2880000
0*
#2885000
b10110001 !
b10110001 /
b10110001 ,
b100011111 .
1*
#2890000
0*
#2895000
b10110010 !
b10110010 /
b10110010 ,
b100100000 .
1*
#2900000
0*
#2905000
b10110011 !
b10110011 /
b10110011 ,
b100100001 .
1*
#2910000
0*
#2915000
b10110100 !
b10110100 /
b10110100 ,
b100100010 .
1*
#2920000
0*
#2925000
b10110101 !
b10110101 /
b10110101 ,
b100100011 .
1*
#2930000
0*
#2935000
b10110110 !
b10110110 /
b10110110 ,
b100100100 .
1*
#2940000
0*
#2945000
b10110111 !
b10110111 /
b10110111 ,
b100100101 .
1*
#2950000
0*
#2955000
b10111000 !
b10111000 /
b10111000 ,
b100100110 .
1*
#2960000
0*
#2965000
b10111001 !
b10111001 /
b10111001 ,
b100100111 .
1*
#2970000
0*
#2975000
b10111010 !
b10111010 /
b10111010 ,
b100101000 .
1*
#2980000
0*
#2985000
b10111011 !
b10111011 /
b10111011 ,
b100101001 .
1*
#2990000
0*
#2995000
b10111100 !
b10111100 /
b10111100 ,
b100101010 .
1*
#3000000
0*
#3005000
b10111101 !
b10111101 /
b10111101 ,
b100101011 .
1*
#3010000
0*
#3015000
b10111110 !
b10111110 /
b10111110 ,
b100101100 .
1*
#3020000
0*
#3025000
b10111111 !
b10111111 /
b10111111 ,
b100101101 .
1*
#3030000
0*
#3035000
b11000000 !
b11000000 /
b11000000 ,
b100101110 .
1*
#3040000
0*
#3045000
b11000001 !
b11000001 /
b11000001 ,
b100101111 .
1*
#3050000
0*
#3055000
b11000010 !
b11000010 /
b11000010 ,
b100110000 .
1*
#3060000
0*
#3065000
b11000011 !
b11000011 /
b11000011 ,
b100110001 .
1*
#3070000
0*
#3075000
b11000100 !
b11000100 /
b11000100 ,
b100110010 .
1*
#3080000
0*
#3085000
b11000101 !
b11000101 /
b11000101 ,
b100110011 .
1*
#3090000
0*
#3095000
b11000110 !
b11000110 /
b11000110 ,
b100110100 .
1*
#3100000
0*
#3105000
b11000111 !
b11000111 /
b11000111 ,
b100110101 .
1*
#3110000
0*
#3115000
b11001000 !
b11001000 /
b11001000 ,
b100110110 .
1*
#3120000
0*
#3125000
b11001001 !
b11001001 /
b11001001 ,
b100110111 .
1*
#3130000
0*
#3135000
b11001010 !
b11001010 /
b11001010 ,
b100111000 .
1*
#3140000
0*
#3145000
b11001011 !
b11001011 /
b11001011 ,
b100111001 .
1*
#3150000
0*
#3155000
b11001100 !
b11001100 /
b11001100 ,
b100111010 .
1*
#3160000
0*
#3165000
b11001101 !
b11001101 /
b11001101 ,
b100111011 .
1*
#3170000
0*
#3175000
b11001110 !
b11001110 /
b11001110 ,
b100111100 .
1*
#3180000
0*
#3185000
b11001111 !
b11001111 /
b11001111 ,
b100111101 .
1*
#3190000
0*
#3195000
b11010000 !
b11010000 /
b11010000 ,
b100111110 .
1*
#3200000
0*
#3205000
b11010001 !
b11010001 /
b11010001 ,
b100111111 .
1*
#3210000
0*
#3215000
b11010010 !
b11010010 /
b11010010 ,
b101000000 .
1*
#3220000
0*
#3225000
b11010011 !
b11010011 /
b11010011 ,
b101000001 .
1*
#3230000
0*
#3235000
b11010100 !
b11010100 /
b11010100 ,
b101000010 .
1*
#3240000
0*
#3245000
b11010101 !
b11010101 /
b11010101 ,
b101000011 .
1*
#3250000
0*
#3255000
b11010110 !
b11010110 /
b11010110 ,
b101000100 .
1*
#3260000
0*
#3265000
b11010111 !
b11010111 /
b11010111 ,
b101000101 .
1*
#3270000
0*
#3275000
b11011000 !
b11011000 /
b11011000 ,
b101000110 .
1*
#3280000
0*
#3285000
b11011001 !
b11011001 /
b11011001 ,
b101000111 .
1*
#3290000
0*
#3295000
b11011010 !
b11011010 /
b11011010 ,
b101001000 .
1*
#3300000
0*
#3305000
b11011011 !
b11011011 /
b11011011 ,
b101001001 .
1*
#3310000
0*
#3315000
b11011100 !
b11011100 /
b11011100 ,
b101001010 .
1*
#3320000
0*
#3325000
b11011101 !
b11011101 /
b11011101 ,
b101001011 .
1*
#3330000
0*
#3335000
b11011110 !
b11011110 /
b11011110 ,
b101001100 .
1*
#3340000
0*
#3345000
b11011111 !
b11011111 /
b11011111 ,
b101001101 .
1*
#3350000
0*
#3355000
b11100000 !
b11100000 /
b11100000 ,
b101001110 .
1*
#3360000
0*
#3365000
b11100001 !
b11100001 /
b11100001 ,
b101001111 .
1*
#3370000
0*
#3375000
b11100010 !
b11100010 /
b11100010 ,
b101010000 .
1*
#3380000
0*
#3385000
b11100011 !
b11100011 /
b11100011 ,
b101010001 .
1*
#3390000
0*
#3395000
b11100100 !
b11100100 /
b11100100 ,
b101010010 .
1*
#3400000
0*
#3405000
b11100101 !
b11100101 /
b11100101 ,
b101010011 .
1*
